kvvmail/__init__.py
kvvmail-0.0.1.dist-info/LICENCE.txt
kvvmail-0.0.1.dist-info/METADATA
kvvmail-0.0.1.dist-info/WHEEL
kvvmail-0.0.1.dist-info/top_level.txt
kvvmail-0.0.1.dist-info/RECORD
