Metadata-Version: 2.1
Name: kvvmail
Version: 0.0.1
Summary: simplified code of sending mail
Home-page: UNKNOWN
Author: krupal vora
Author-email: krupal.vora@sakec.ac.in
License: UNKNOWN
Keywords: kvvmail
Platform: UNKNOWN
Classifier: Intended Audience :: Education
Classifier: License :: OSI Approved :: MIT License
Requires-Dist: smtplib
